LICENSE
README.rst
setup.py
superset/views/gcp_cloud/__init__.py
superset/views/gcp_cloud/decorators.py
superset/views/gcp_cloud/views.py
superset_gcp_cloud.egg-info/PKG-INFO
superset_gcp_cloud.egg-info/SOURCES.txt
superset_gcp_cloud.egg-info/dependency_links.txt
superset_gcp_cloud.egg-info/top_level.txt