Metadata-Version: 2.1
Name: superset-gcp-cloud
Version: 1.0.1
Summary: A Superset gcp cloud plugin
Home-page: UNKNOWN
Author: Avinash Katariya
Author-email: akatariya@quotient.com
License: Apache 2.0
Platform: UNKNOWN
Classifier: Programming Language :: Python :: 3
Classifier: License :: OSI Approved :: MIT License
Classifier: Operating System :: OS Independent
Requires-Python: >=3.6
License-File: LICENSE
